pulumi_vcd/__init__.py
pulumi_vcd/_inputs.py
pulumi_vcd/_utilities.py
pulumi_vcd/api_filter.py
pulumi_vcd/api_token.py
pulumi_vcd/catalog.py
pulumi_vcd/catalog_access_control.py
pulumi_vcd/catalog_item.py
pulumi_vcd/catalog_media.py
pulumi_vcd/catalog_vapp_template.py
pulumi_vcd/cloned_vapp.py
pulumi_vcd/cse_kubernetes_cluster.py
pulumi_vcd/dse_registry_configuration.py
pulumi_vcd/dse_solution_publish.py
pulumi_vcd/edgegateway.py
pulumi_vcd/edgegateway_settings.py
pulumi_vcd/edgegateway_vpn.py
pulumi_vcd/external_endpoint.py
pulumi_vcd/external_network.py
pulumi_vcd/external_network_v2.py
pulumi_vcd/get_api_filter.py
pulumi_vcd/get_catalog.py
pulumi_vcd/get_catalog_access_control.py
pulumi_vcd/get_catalog_item.py
pulumi_vcd/get_catalog_media.py
pulumi_vcd/get_catalog_vapp_template.py
pulumi_vcd/get_cse_kubernetes_cluster.py
pulumi_vcd/get_dse_registry_configuration.py
pulumi_vcd/get_dse_solution_publish.py
pulumi_vcd/get_edgegateway.py
pulumi_vcd/get_external_endpoint.py
pulumi_vcd/get_external_network.py
pulumi_vcd/get_external_network_v2.py
pulumi_vcd/get_global_role.py
pulumi_vcd/get_independent_disk.py
pulumi_vcd/get_ip_space.py
pulumi_vcd/get_ip_space_custom_quota.py
pulumi_vcd/get_ip_space_ip_allocation.py
pulumi_vcd/get_ip_space_uplink.py
pulumi_vcd/get_lb_app_profile.py
pulumi_vcd/get_lb_app_rule.py
pulumi_vcd/get_lb_server_pool.py
pulumi_vcd/get_lb_service_monitor.py
pulumi_vcd/get_lb_virtual_server.py
pulumi_vcd/get_library_certificate.py
pulumi_vcd/get_multisite_org_association.py
pulumi_vcd/get_multisite_org_data.py
pulumi_vcd/get_multisite_site.py
pulumi_vcd/get_multisite_site_association.py
pulumi_vcd/get_multisite_site_data.py
pulumi_vcd/get_network_direct.py
pulumi_vcd/get_network_isolated.py
pulumi_vcd/get_network_isolated_v2.py
pulumi_vcd/get_network_pool.py
pulumi_vcd/get_network_routed.py
pulumi_vcd/get_network_routed_v2.py
pulumi_vcd/get_nsxt_alb_cloud.py
pulumi_vcd/get_nsxt_alb_controller.py
pulumi_vcd-1.0.0.dist-info/METADATA
pulumi_vcd-1.0.0.dist-info/WHEEL
pulumi_vcd-1.0.0.dist-info/top_level.txt
pulumi_vcd-1.0.0.dist-info/RECORD
